effective_py/__init__.py
effective_py/enum.py
tests/__init__.py
effective_py-0.1.2.dist-info/LICENSE
effective_py-0.1.2.dist-info/METADATA
effective_py-0.1.2.dist-info/WHEEL
effective_py-0.1.2.dist-info/top_level.txt
effective_py-0.1.2.dist-info/RECORD
