Metadata-Version: 2.1
Name: effective-py
Version: 0.1.2
Summary: Extension for Python simulate other program language
Home-page: https://github.com/mikezone/effective-py
Author: mike_chang
Author-email: 82643885@qq.com
Maintainer: mike_chang
Maintainer-email: 82643885@qq.com
License: MIT
Project-URL: Documentation, https://github.com/mikezone/effective-py
Project-URL: Code, https://github.com/mikezone/effective-py
Project-URL: Issue tracker, https://github.com/mikezone/effective-py/issues
Platform: UNKNOWN
Classifier: Environment :: Web Environment
Classifier: Intended Audience :: Developers
Classifier: License :: OSI Approved :: MIT License
Classifier: Operating System :: OS Independent
Classifier: Programming Language :: Python :: 3
Classifier: Topic :: Internet :: WWW/HTTP :: Dynamic Content
Classifier: Topic :: Software Development :: Libraries :: Python Modules
Requires-Python: >=3.7
Requires-Dist: six (>=1.16.0)
